Authors
ChangeLog
License
MANIFEST
setup.py
RosterCore.egg-info/PKG-INFO
RosterCore.egg-info/SOURCES.txt
RosterCore.egg-info/dependency_links.txt
RosterCore.egg-info/requires.txt
RosterCore.egg-info/top_level.txt
docs/html/.buildinfo
docs/html/genindex.html
docs/html/index.html
docs/html/objects.inv
docs/html/py-modindex.html
docs/html/roster_core.html
docs/html/search.html
docs/html/searchindex.js
docs/html/_modules/index.html
docs/html/_modules/roster_core/__init__.html
docs/html/_modules/roster_core/audit_log.html
docs/html/_modules/roster_core/config.html
docs/html/_modules/roster_core/core.html
docs/html/_modules/roster_core/core_helpers.html
docs/html/_modules/roster_core/data_validation.html
docs/html/_modules/roster_core/db_access.html
docs/html/_modules/roster_core/errors.html
docs/html/_modules/roster_core/helpers_lib.html
docs/html/_modules/roster_core/punycode_lib.html
docs/html/_modules/roster_core/user.html
docs/html/_sources/index.txt
docs/html/_sources/roster_core.txt
docs/html/_static/ajax-loader.gif
docs/html/_static/basic.css
docs/html/_static/comment-bright.png
docs/html/_static/comment-close.png
docs/html/_static/comment.png
docs/html/_static/default.css
docs/html/_static/doctools.js
docs/html/_static/down-pressed.png
docs/html/_static/down.png
docs/html/_static/file.png
docs/html/_static/jquery.js
docs/html/_static/minus.png
docs/html/_static/plus.png
docs/html/_static/pygments.css
docs/html/_static/searchtools.js
docs/html/_static/sidebar.js
docs/html/_static/underscore.js
docs/html/_static/up-pressed.png
docs/html/_static/up.png
docs/html/_static/websupport.js
roster_core/__init__.py
roster_core/audit_log.py
roster_core/config.py
roster_core/constants.py
roster_core/core.py
roster_core/core_helpers.py
roster_core/data_validation.py
roster_core/db_access.py
roster_core/embedded_files.py
roster_core/errors.py
roster_core/helpers_lib.py
roster_core/punycode_lib.py
roster_core/user.py
scripts/roster_database_bootstrap